pyunitsystem/__init__.py
pyunitsystem/electriccurrentsystem.py
pyunitsystem/energysystem.py
pyunitsystem/metricsystem.py
pyunitsystem/timesystem.py
pyunitsystem/unit.py
pyunitsystem/voltagesystem.py
pyunitsystem/test/test_unitsystem.py
pyunitsystem-2.0.0.dist-info/LICENSE
pyunitsystem-2.0.0.dist-info/METADATA
pyunitsystem-2.0.0.dist-info/WHEEL
pyunitsystem-2.0.0.dist-info/top_level.txt
pyunitsystem-2.0.0.dist-info/RECORD
