Metadata-Version: 2.1
Name: pyunitsystem
Version: 2.0.0
Summary: dummy unit system
Author-email: Henri Payno <henri.payno@esrf.fr>, Pierre Paleo <pierre.paleo@esrf.fr>, Alessandro Mirone <mirone@esrf.fr>, Jérôme Lesaint <jerome.lesaint@esrf.fr>
License: 
Project-URL: Homepage, https://gitlab.esrf.fr/tomotools/pyunitsystem
Project-URL: Repository, https://gitlab.esrf.fr/tomotools/pyunitsystem
Project-URL: Changelog, https://gitlab.esrf.fr/tomotools/pyunitsystem/-/blob/master/CHANGELOG.md
Keywords: tomotools,unit system
Classifier: Development Status :: 5 - Production/Stable
Classifier: Intended Audience :: Developers
Classifier: Intended Audience :: Science/Research
Classifier: Programming Language :: Python :: 3
Classifier: Programming Language :: Python :: 3.7
Classifier: Programming Language :: Python :: 3.8
Classifier: Programming Language :: Python :: 3.9
Classifier: Programming Language :: Python :: 3.10
Classifier: Programming Language :: Python :: 3.11
Classifier: Programming Language :: Python :: 3.12
Classifier: Environment :: Console
Classifier: License :: OSI Approved :: MIT License
Classifier: Operating System :: Unix
Classifier: Operating System :: MacOS :: MacOS X
Classifier: Operating System :: POSIX
Classifier: Topic :: Scientific/Engineering :: Physics
Classifier: Topic :: Scientific/Engineering :: Medical Science Apps.
Requires-Python: >=3.7
License-File: LICENSE
Provides-Extra: test
Requires-Dist: pytest ; extra == 'test'
Requires-Dist: pytest-cov ; extra == 'test'
